Workbook
Name Slicer_Account: #N/A

Sheet Charts of Accounts
A1: Accounts | C1: Accounts | D1: Sub Accounts | E1: Financial Statement | G1: Individual Accounts | H1: Sub Accounts
A2: Assets | C2: Assets | D2: Current Assets | E2: Balance Sheet | G2: Cash | H2: Current Assets
A3: Liabilities | C3: Assets | D3: Fixed Assets | E3: Balance Sheet | G3: Equity - Owais | H3: Equity
A4: Equity | C4: Liabilities | D4: Current Liabilities | E4: Balance Sheet | G4: Bank - 1122 | H4: Current Assets
A5: Expenses | C5: Liabilities | D5: Fixed Liabilities | E5: Balance Sheet | G5: Inventory | H5: Current Assets
A6: Revenue | C6: Equity | D6: Equity | E6: Balance Sheet | G6: Mr. Ayo | H6: Current Liabilities
C7: Expenses | D7: Expenses | E7: Income Statement | G7: Sales | H7: Revenue
C8: Revenue | D8: Revenue | E8: Income Statement | G8: Cost of Goods Sold | H8: Expenses
C9: Revenue | D9: Contra Revenue | E9: Income Statement | G9: Paul | H9: Current Assets
G10: Electricity | H10: Expenses
G11: Salary | H11: Expenses
G12: Taxes | H12: Expenses
G13: Govt | H13: Current Liabilities
G14: Shop | H14: Fixed Assets

Sheet General Entries
B2: Date | C2: Description | D2: Account | E2: Debit | F2: Credit | G2: Comments
B3: 44927 | C3: Establishing a Business | D3: Cash | E3: 1000000
B4: 44927 | C4: Establishing a Business | D4: Equity - Owais | F4: 1000000
B5: 44928 | C5: Deposit into Bank | D5: Bank - 1122 | E5: 500000 | G5: Mr. Kunle went to bank to deposit
B6: 44928 | C6: Deposit into Bank | D6: Cash | F6: 500000 | G6: Mr. Kunle went to bank to deposit
B7: 44929 | C7: Purchased Inventory | D7: Inventory | E7: 600000
B8: 44929 | C8: Purchased Inventory | D8: Mr. Ayo | F8: 600000
B9: 44930 | C9: Purchased Inventory | D9: Inventory | E9: 200000
B10: 44930 | C10: Purchased Inventory | D10: Bank - 1122 | F10: 200000
B11: 44936 | C11: Sold Inventory for Cash | D11: Cash | E11: 400000
B12: 44936 | C12: Sold Inventory for Cash | D12: Sales | F12: 400000
B13: 44936 | C13: Adjust Inventory Against COGS | D13: Cost of Goods Sold | E13: 300000
B14: 44936 | C14: Adjust Inventory Against COGS | D14: Inventory | F14: 300000
B15: 44941 | C15: Sold Inventory on Credit | D15: Paul | E15: 300000
B16: 44941 | C16: Sold Inventory on Credit | D16: Sales | F16: 300000
B17: 44941 | C17: Adjust Inventory Against COGS | D17: Cost of Goods Sold | E17: 150000
B18: 44941 | C18: Adjust Inventory Against COGS | D18: Inventory | F18: 150000
B19: 44944 | C19: Paid Electricity | D19: Electricity | E19: 15000
B20: 44944 | C20: Paid Electricity | D20: Bank - 1122 | F20: 15000
B21: 44956 | C21: Paid Salaries | D21: Salary | E21: 100000
B22: 44956 | C22: Paid Salaries | D22: Cash | F22: 100000
B23: 44959 | C23: Paid to Mr. Ayo | D23: Mr. Ayo | E23: 100000
B24: 44959 | C24: Paid to Mr. Ayo | D24: Cash | F24: 100000
B25: 44962 | C25: Received from Mr. Paul | D25: Bank - 1122 | E25: 150000
B26: 44962 | C26: Received from Mr. Paul | D26: Paul | F26: 150000
B27: 44967 | C27: Purchased a Shop | D27: Shop | E27: 100000
B28: 44967 | C28: Purchased a Shop | D28: Cash | F28: 100000
B29: 45015 | C29: Payable Taxes to Govt | D29: Taxes | E29: 20250
B30: 45015 | C30: Payable Taxes to Govt | D30: Govt | F30: 20250

Sheet Ledger
B3: =C5 -> Cash | D3: =VLOOKUP(Ledger!B3,'Charts of Accounts'!G:H,2,0) -> Current Assets
B4: Date | C4: Account | D4: Description | E4: Sum of Debit | F4: Sum of Credit | G4: Sum of Balance
B5: 44927 | C5: Cash | D5: Establishing a Business | E5: 1000000 | G5: 1000000
B6: 44927 | C6: Equity - Owais | D6: Establishing a Business | F6: 1000000 | G6: -1000000
B7: 44928 | C7: Bank - 1122 | D7: Deposit into Bank | E7: 500000 | G7: 500000
B8: 44928 | C8: Cash | D8: Deposit into Bank | F8: 500000 | G8: -500000
B9: 44929 | C9: Inventory | D9: Purchased Inventory | E9: 600000 | G9: 600000
B10: 44929 | C10: Mr. Ayo | D10: Purchased Inventory | F10: 600000 | G10: -600000
B11: 44930 | C11: Bank - 1122 | D11: Purchased Inventory | F11: 200000 | G11: -200000
B12: 44930 | C12: Inventory | D12: Purchased Inventory | E12: 200000 | G12: 200000
B13: 44936 | C13: Cash | D13: Sold Inventory for Cash | E13: 400000 | G13: 400000
B14: 44936 | C14: Cost of Goods Sold | D14: Adjust Inventory Against COGS | E14: 300000 | G14: 300000
B15: 44936 | C15: Inventory | D15: Adjust Inventory Against COGS | F15: 300000 | G15: -300000
B16: 44936 | C16: Sales | D16: Sold Inventory for Cash | F16: 400000 | G16: -400000
B17: 44941 | C17: Cost of Goods Sold | D17: Adjust Inventory Against COGS | E17: 150000 | G17: 150000
B18: 44941 | C18: Inventory | D18: Adjust Inventory Against COGS | F18: 150000 | G18: -150000
B19: 44941 | C19: Paul | D19: Sold Inventory on Credit | E19: 300000 | G19: 300000
B20: 44941 | C20: Sales | D20: Sold Inventory on Credit | F20: 300000 | G20: -300000
B21: 44944 | C21: Bank - 1122 | D21: Paid Electricity | F21: 15000 | G21: -15000
B22: 44944 | C22: Electricity | D22: Paid Electricity | E22: 15000 | G22: 15000
B23: 44956 | C23: Cash | D23: Paid Salaries | F23: 100000 | G23: -100000
B24: 44956 | C24: Salary | D24: Paid Salaries | E24: 100000 | G24: 100000
B25: 44959 | C25: Cash | D25: Paid to Mr. Ayo | F25: 100000 | G25: -100000
B26: 44959 | C26: Mr. Ayo | D26: Paid to Mr. Ayo | E26: 100000 | G26: 100000
B27: 44962 | C27: Bank - 1122 | D27: Received from Mr. Paul | E27: 150000 | G27: 150000
B28: 44962 | C28: Paul | D28: Received from Mr. Paul | F28: 150000 | G28: -150000
B29: 45015 | C29: Taxes | D29: Payable Taxes to Govt | E29: 20250 | G29: 20250
B30: 45015 | C30: Govt | D30: Payable Taxes to Govt | F30: 20250 | G30: -20250
B31: 44967 | C31: Cash | D31: Purchased a Shop | F31: 100000 | G31: -100000
B32: 44967 | C32: Shop | D32: Purchased a Shop | E32: 100000 | G32: 100000
B33: Grand Total | E33: 3935250 | F33: 3935250 | G33: 0

Sheet Trial Balance
B3: TRAIL BALANCE
B4: Account | C4: Sum of Debit | D4: Sum of Credit | E4: Sum of Balance
B5: Bank - 1122 | C5: 650000 | D5: 215000 | E5: 435000
B6: Cash | C6: 1400000 | D6: 800000 | E6: 600000
B7: Cost of Goods Sold | C7: 450000 | E7: 450000
B8: Electricity | C8: 15000 | E8: 15000
B9: Equity - Owais | D9: 1000000 | E9: -1000000
B10: Inventory | C10: 800000 | D10: 450000 | E10: 350000
B11: Mr. Ayo | C11: 100000 | D11: 600000 | E11: -500000
B12: Paul | C12: 300000 | D12: 150000 | E12: 150000
B13: Salary | C13: 100000 | E13: 100000
B14: Sales | D14: 700000 | E14: -700000
B15: Taxes | C15: 20250 | E15: 20250
B16: Govt | D16: 20250 | E16: -20250
B17: Shop | C17: 100000 | E17: 100000
B18: Grand Total | C18: 3935250 | D18: 3935250 | E18: 0

Sheet Income Statement
B2: MR. OWAIS LTD
B3: INCOME STATEMENT
B4: for the period 1st Jan. 2023 to 31st Mar 2023
C6: Sales | F6: =VLOOKUP(C6,'Trial Balance'!$B$5:$E$14,4,0)*-1 -> 700000
C7: Cost of Goods Sold | F7: =VLOOKUP(C7,'Trial Balance'!$B$5:$E$14,4,0)*-1 -> -450000
C8: Gross Profit | F8: =F6+F7 -> 250000
C10: OPERATING EXPENSES
C12: Salary | E12: =VLOOKUP(C12,'Trial Balance'!$B$5:$E$14,4,0) -> 100000
C13: Electricity | E13: =VLOOKUP(C13,'Trial Balance'!$B$5:$E$14,4,0) -> 15000
C14: Total of Operating Expenses | F14: =(E12+E13)*-1 -> -115000
C15: Operating Profit | F15: =F8+F14 -> 135000
C16: Taxes(15%) | F16: =(F15*0.15)*-1 -> -20250
C17: Net Profit | F17: =F15+F16 -> 114750

Sheet Balance Sheet
B2: Mr. Owais Ltd
B3: Balance Sheet
B4: as on 30 Mar 2023
B6: Assets | F6: Liabilities & Equities
F8: Liabilities
B9: Fixed Assets | F9: Fixed Liabilities
B10: Shop | D10: =VLOOKUP(B10,'Trial Balance'!$B$5:$E$17,4,0) -> 100000 | I10: 0
B11: Total of Fixed Assets | E11: 100000
B13: Current Assets | F13: Current Liabilities
B14: Bank - 1122 | D14: =VLOOKUP(B14,'Trial Balance'!$B$5:$E$17,4,0) -> 435000 | F14: Mr. Ayo | H14: =VLOOKUP(F14,'Trial Balance'!$B$5:$E$17,4,0)*-1 -> 500000
B15: Cash | D15: =VLOOKUP(B15,'Trial Balance'!$B$5:$E$17,4,0) -> 600000 | F15: Govt | H15: =VLOOKUP(F15,'Trial Balance'!$B$5:$E$17,4,0)*-1 -> 20250
B16: Inventory | D16: =VLOOKUP(B16,'Trial Balance'!$B$5:$E$17,4,0) -> 350000 | F16: Total of Current Liabilities | I16: =SUM(H13:H15) -> 520250
B17: Paul | D17: =VLOOKUP(B17,'Trial Balance'!$B$5:$E$17,4,0) -> 150000
B18: Total of Current Assets | E18: =SUM(D14:D17) -> 1535000 | F18: TOTAL OF LIABILITIES | I18: 520250
F23: Equity
F24: Equity - Owais | H24: =VLOOKUP(F24,'Trial Balance'!$B$5:$E$17,4,0)*-1 -> 1000000
F25: Retain Earning | H25: ='Income Statement'!F17 -> 114750
F26: Total of Equity | I26: =H25+H24 -> 1114750
B29: TOTAL OF ASSETS | E29: =E18+E11 -> 1635000 | F29: TOTAL OF LIABILITIES + EQUITY | I29: =I26+I18 -> 1635000
